main.py
unsee_dl/__init__.py
unsee_dl/names.py
unsee_dl/unsee.py
unsee_dl/unsee_new.py
unsee_dl/unsee_old.py
unsee_dl-1.3.2.dist-info/entry_points.txt
unsee_dl-1.3.2.dist-info/LICENSE
unsee_dl-1.3.2.dist-info/WHEEL
unsee_dl-1.3.2.dist-info/METADATA
unsee_dl-1.3.2.dist-info/RECORD
