Metadata-Version: 2.1
Name: unsee-dl
Version: 1.3.2
Summary: unsee.cc downloader
Home-page: https://github.com/andsala/unsee-dl
License: MIT
Keywords: unsee,download
Author: Andrea Salamone
Author-email: andrea.sala96@gmail.com
Requires-Python: >=3.6,<4.0
Classifier: Development Status :: 4 - Beta
Classifier: Environment :: Console
Classifier: License :: OSI Approved :: MIT License
Classifier: Programming Language :: Python :: 3
Classifier: Programming Language :: Python :: 3.6
Classifier: Programming Language :: Python :: 3.7
Classifier: Programming Language :: Python :: 3.8
Classifier: Programming Language :: Python :: 3.9
Classifier: Topic :: Utilities
Requires-Dist: aiohttp (>=3.6.2,<4.0.0)
Requires-Dist: cchardet (>=2.1.6,<3.0.0)
Project-URL: Repository, https://github.com/andsala/unsee-dl
